django_coffee_model/__init__.py
django_coffee_model/apps.py
django_coffee_model/models.py
django_coffee_model/migrations/__init__.py
django_coffee_model-2.1.9.dist-info/METADATA
django_coffee_model-2.1.9.dist-info/WHEEL
django_coffee_model-2.1.9.dist-info/top_level.txt
django_coffee_model-2.1.9.dist-info/RECORD
